ipyp5/__init__.py
ipyp5/_frontend.py
ipyp5/_version.py
ipyp5/sketch.py
ipyp5/labextension/jupyter-p5-0.1.1.tgz
ipyp5/nbextension/__init__.py
ipyp5/nbextension/static/extension.js
ipyp5/nbextension/static/index.js
ipyp5/nbextension/static/index.js.map
ipyp5-0.1.1.data/data/etc/jupyter/nbconfig/notebook.d/jupyter-p5.json
ipyp5-0.1.1.data/data/share/jupyter/lab/extensions/jupyter-p5-0.1.1.tgz
ipyp5-0.1.1.data/data/share/jupyter/nbextensions/jupyter-p5/extension.js
ipyp5-0.1.1.data/data/share/jupyter/nbextensions/jupyter-p5/index.js
ipyp5-0.1.1.data/data/share/jupyter/nbextensions/jupyter-p5/index.js.map
ipyp5-0.1.1.dist-info/LICENSE.txt
ipyp5-0.1.1.dist-info/METADATA
ipyp5-0.1.1.dist-info/WHEEL
ipyp5-0.1.1.dist-info/top_level.txt
ipyp5-0.1.1.dist-info/RECORD
